Metadata-Version: 1.0
Name: gsnd-probability
Version: 0.1
Summary: Gaussian and Binomial distributions
Home-page: UNKNOWN
Author: Jarnen Richard
Author-email: UNKNOWN
License: UNKNOWN
Platform: UNKNOWN
